rsaidnumber/__init__.py
rsaidnumber/constants.py
rsaidnumber/random.py
rsa_id_number-0.1.0.dist-info/WHEEL
rsa_id_number-0.1.0.dist-info/METADATA
rsa_id_number-0.1.0.dist-info/RECORD
