Metadata-Version: 2.4
Name: rsa-id-number
Version: 0.1.0
Summary: South African ID number utilities
Keywords: utilities,development
Author: Teamgeek
Author-email: Teamgeek <support@teamgeek.io>
License-Expression: MIT
Classifier: Development Status :: 3 - Alpha
Classifier: Intended Audience :: Developers
Classifier: Topic :: Software Development :: Libraries
Classifier: License :: OSI Approved :: MIT License
Classifier: Programming Language :: Python :: 3
Requires-Python: >=3.11
Project-URL: Homepage, https://github.com/teamgeek-io/rsa-id-number
Project-URL: Issues, https://github.com/teamgeek-io/rsa-id-number/issues
